<data>
  <id><![CDATA[50462876]]></id>
  <url><![CDATA[https://mp.weixin.qq.com/s?timestamp=1540374249&src=3&ver=1&signature=RY2k6HF623UG39sDmTM6AaU46HmwmXBJj*kYsW-IYQsSZNymvbl0tn8UYIOGeSniwR4cpwsQXaKu9V8zZmnv9WvdH0CsxTTO*6m*QFqfnR1a*C4RnjZGeYwmFqs74qUC1LDSEdQcwwfm7OMpJhUKVPAW7pOrF2gpdVPixSj3duQ=]]></url>
  <title><![CDATA[印度最牛的10种开挂模式：挂火车只能排第9，第1名才要命]]></title>
  <content><![CDATA[请关注读史君个人微信：dushi8115印度人的疯狂举动常常用阿三开挂来形容。除了我们最常见的挂火车之外，还有很多不被常人所理解的行为，网友票选的印度十大开挂行为。第十名，街头魔术师表演身体悬空，奥秘就是他的袖子里。第九名：挂火车。在印度，火车是主要出行方式，但印度人口众多，火车班次又少，买不到坐票的人，可以买挂票，所以就出现了如此的奇观。当然印度的火车速度很慢。第八名：露天厕所。据统计，在印度，厕所与人口存在比例万分之一，平均万个人才有一个厕所，也就造成了大多数人有随地大小便的习惯。第七名：印度杂技团。摩托车载人是杂技团的常规表演项目，一辆车载几十个人都不在话下，甚至还可以在车上表演高难度的头顶人。第六名：印度士兵火焰钢管舞。印度士兵的日常训练除了胸口碎大石和徒手劈砖外，还要在钢管上表演火焰舞。第五名：恒河水。恒河是印度发源地，尽管这些年来，恒河污染严重，人们依旧会来这里沐浴和饮用。第四名：求雨。印度干旱少雨，每年都要进行求雨的仪式。求雨的方式也很特别，手拿一根棍夹在脚趾，光膀子围成一个圈躺在地上，每次都有不少人中暑。第三名：打男人节。每年的3月份，是印度的打男人节，在这一天，妇女们可以拿着木棍随意打路过的男人，偶尔会有人被打骨折。第二名：开挂穿刺。印度的盘古尼尤素姆节，一些信徒会在自己的身上插满铁钎，这样做是为了带来健康和好运。第一名：被牛踩。在印度，牛被他们奉为神灵。每年的阿纳库特神节上，人们都会躺在地方，让头戴花环的牛在自己身上踩来踩去，在他们看来，被神踩踏是幸运的。很多人轻者骨折受伤，重则当场暴毙。后语：大量粉丝还没有养成阅读后点赞的习惯，希望大家在阅读后顺便点赞，以示鼓励！坚持是一种信仰，专注是一种态度！【推荐】一个有品质的公众号，长按二维码关注TA吧。]]></content>
  <author><![CDATA[读史论道]]></author>
  <time>2018-10-17 21:54:54</time>
  <account><![CDATA[dushilundao]]></account>
</data>
