<data>
  <id><![CDATA[51154485]]></id>
  <url><![CDATA[https://mp.weixin.qq.com/s?timestamp=1540205557&src=3&ver=1&signature=*9qPsj7x5og4*ExcLTDQ8SvHMjlXpqgqslxCLG-DWAx*obgNb0HM0jH9S3Om0kWGRJ-h3WAAH1ugchVK-5r-ayOMyUngfsUEjJILeLCttYuesMPuogIkargH*LDgDfdcIyuKxrYDt7NmIPnruD9*j2eHCTn8HotwJ6P5Y4QDBbM=]]></url>
  <title><![CDATA[赞！2019年医保缴费可以网上自助办理啦！]]></title>
  <content><![CDATA[碣石的亲2019年城乡居民医保个人缴费已经开始！以往要缴费只有两种途径一是凭户口簿和身份证到户籍所在地乡镇或村（社区）参保缴费二是用社保卡到乡镇人社所、医保经办点自助缴费机参保缴费而今年有更方便、更快捷的第三种途径啦下载“汕尾人社”app上，在家即可参保缴费（长按识别图中二维码点击下载）下载安装后，具体操作流程如下：注册账号设置密码，账号即是身份证号码可选择自己参保缴费，也可帮家人朋友参保缴费⬇️⬇️添加参保人员只需输入姓名和身份证号码⬇️⬇️核对参保人员和缴费信息点击确认缴费⬇️⬇️缴费方式有微信支付和支付宝支付两种，在家即可参保缴费⬇️⬇️注意参保缴费时间是2018年10月初至12月底哦记得在规定时间内及时进行参保推广]]></content>
  <author><![CDATA[碣石商务中心]]></author>
  <time>2018-10-14 19:59:02</time>
  <account><![CDATA[jssw0660]]></account>
</data>
