<data>
  <id><![CDATA[51175546]]></id>
  <url><![CDATA[https://mp.weixin.qq.com/s?timestamp=1542765816&src=3&ver=1&signature=13KCscf5UL5YYmNalCloNAIFIV0ONq76-vyY8*jhf4F2Iv6hn40V3LLYc-jUnUIOR32RyVedDM4p*NwLc8Ni-P*hH-3DgN7S7vaI12lDDh*o9uFPX07Tj4AkbcKo78GC-B7bfAlefheqBThh2xuIJV7cjQnxar7FEGxbSA5r*HE=]]></url>
  <title><![CDATA[他在少林修行几十年，说出了少林功夫的真相]]></title>
  <content><![CDATA[]]></content>
  <author><![CDATA[功夫咏春]]></author>
  <time>2018-11-20 22:25:17</time>
  <account><![CDATA[gfyongchun]]></account>
  <image><![CDATA[]]></image>
</data>
