<data>
  <id><![CDATA[52226617]]></id>
  <url><![CDATA[https://mp.weixin.qq.com/s?timestamp=1542698106&src=3&ver=1&signature=0LXEzj6OCQ-EI1A7OJKr6hHcCifmljXkSDYmiIMJw-TQX89M5pLGYCrY42WSsRGJxg1iT*N*md9mxXDpSLZ1HNoBKKBtAva42N0*wzq2UvWQgY3rhHuKN1PWUoFANo6D5QeN1NvRiIcTkoyhIVh77TAjZVixaR*AEBGyV1wpti0=]]></url>
  <title><![CDATA[掌中微传媒]]></title>
  <content><![CDATA[]]></content>
  <author><![CDATA[]]></author>
  <time></time>
  <account><![CDATA[zzwcm888]]></account>
  <image><![CDATA[]]></image>
</data>
