<data>
  <id><![CDATA[116630865]]></id>
  <url><![CDATA[https://mp.weixin.qq.com/s?timestamp=1542110499&src=3&ver=1&signature=FUQlo*EiTcEnr5M8yWfPtjSwVirBiVUo1XMBynuH22Q*Lqf7Y9hCGQK2Bw2m9Ll0NRoURhdummtoi0UpADqLWOrSJsVBXVFTIBmF7oPqI7TdmYAiP9tRuL5Em1rJWzcSLVbTB016FsIXK2noSEqdZ-j*kyURYjg3-96*Cuv1dNw=]]></url>
  <title><![CDATA[前晚11点46分在澄海启航电子室，发生的一幕…]]></title>
  <content><![CDATA[昨晚11点46分在澄海启航电子室，发生的一幕…君子爱财取之有道希望认知自己错误，早日归还来源网友报料 | 澄海100]]></content>
  <author><![CDATA[澄海在线]]></author>
  <time>2018-11-12 16:17:40</time>
  <account><![CDATA[chenhzxiang]]></account>
  <image><![CDATA[]]></image>
</data>
